lavviebot/__init__.py
lavviebot/lavviebotapi.py
lavviebot/cats/__init__.py
lavviebot/cats/cat.py
lavviebot/devices/__init__.py
lavviebot/devices/lavviebot.py
python_lavviebot-0.0.8.dist-info/LICENSE
python_lavviebot-0.0.8.dist-info/METADATA
python_lavviebot-0.0.8.dist-info/WHEEL
python_lavviebot-0.0.8.dist-info/top_level.txt
python_lavviebot-0.0.8.dist-info/RECORD
